ScaleCounter/ScaleCount_Private_Functions.py
ScaleCounter/ScaleCount_Public_Functions.py
ScaleCounter/__init__.py
ScaleCounter-0.0.5.dist-info/LICENSE
ScaleCounter-0.0.5.dist-info/METADATA
ScaleCounter-0.0.5.dist-info/WHEEL
ScaleCounter-0.0.5.dist-info/top_level.txt
ScaleCounter-0.0.5.dist-info/RECORD
