Metadata-Version: 2.1
Name: ScaleCounter
Version: 0.0.5
Summary: A package to count scales on reptiles.
Home-page: https://github.com/tanyasarkinjain/ScaleCount.git
Author: Maggie Cheung, Tanya Jain, Charlie Rettig
Author-email: charlie__r@berkeley.edu
License: UNKNOWN
Project-URL: Bug Tracker, https://github.com/pypa/sampleproject/issues
Platform: UNKNOWN
Classifier: Programming Language :: Python :: 3
Classifier: License :: OSI Approved :: MIT License
Classifier: Operating System :: OS Independent
Requires-Python: >=3.6
License-File: LICENSE
